bscscan_web_api/__init__.py
bscscan_web_api/_parser.py
bscscan_web_api/bscscan.py
bscscan_web_api/models/__init__.py
bscscan_web_api/models/compiler.py
bscscan_web_api/models/recently_added_token.py
bscscan_web_api/models/token.py
bscscan_web_api/models/enums/__init__.py
bscscan_web_api/utils/__init__.py
bscscan_web_api/utils/utils.py
bscscan_web_api-0.0.7.dist-info/LICENSE
bscscan_web_api-0.0.7.dist-info/METADATA
bscscan_web_api-0.0.7.dist-info/WHEEL
bscscan_web_api-0.0.7.dist-info/top_level.txt
bscscan_web_api-0.0.7.dist-info/RECORD
