Metadata-Version: 2.1
Name: bscscan-web-api
Version: 0.0.7
Summary: bscscan_web_api
Home-page: https://github.com/kkristof200/py_bscscan_web_api
Author: Kristóf-Attila Kovács
License: UNKNOWN
Platform: UNKNOWN
Classifier: Programming Language :: Python :: 3.4
Classifier: Programming Language :: Python :: 3.5
Classifier: Programming Language :: Python :: 3.6
Classifier: Programming Language :: Python :: 3.7
Classifier: Programming Language :: Python :: 3.8
Classifier: Programming Language :: Python :: 3.9
Classifier: License :: OSI Approved :: MIT License
Classifier: Operating System :: OS Independent
Requires-Python: >=3.4
License-File: LICENSE
Requires-Dist: beautifulsoup4 (>=4.10.0)
Requires-Dist: jsoncodable (>=0.1.7)
Requires-Dist: ksimpleapi (>=0.0.40)
Requires-Dist: noraise (>=0.0.16)
Requires-Dist: requests (>=2.26.0)
